Workbook

Sheet AIRPORT_DB
A1: ICAO | B1: AIRPORT_NAME | C1: SECTION1B1:L2 | D1: SECTION2 | E1: SECTION3 | F1: 10_AD Elev / Max TMA MSA | G1: Last_Update | H1: Notes | I1: CATEGORY | J1: AD_ELEV_FT | K1: MAX_TMA_MSA_FT | L1: ALT_MSA_COMBINED_SCORE
A2: DAAG | B2: Houari Boumediene Airport (Algiers) | C2: • TRAFFIC: HIGH; PRIMARY ALGERIA HUB; MIXED CIVIL / MIL TRAFFIC • ATC: ACCENT / LANGUAGE VARIATION POSSIBLE; CLEARANCE READBACK IMPORTANT • TAXI: LARGE APRON AREAS; FOLLOW-ME / MARSHALLER COMMON • RWY OPS: INTERSECTING RWY 05/23 AND 09/27; RWY CROSSINGS POSSIBLE • CURFEW: NIGHT RESTRICTIONS MAY APPLY; CHECK AIP/AOI | D2: • METEO: SUMMER HEAT / HAZE COMMON; VISIBILITY REDUCTION POSSIBLE • METEO: OCCASIONAL SAHARA DUST EVENTS • WIND: GUSTY SEA-BREEZE / CROSSWIND POSSIBLE | E2: • SECURITY: ELEVATED SECURITY ENVIRONMENT; MIL PRESENCE POSSIBLE • HANDLING: PRIOR COORDINATION ADVISED FOR BIZAV OPS • FUEL: JET A-1 AVAILABLE; CONFIRM WITH HANDLER • NAV: ILS AVAILABLE; GNSS APPROACHES ALSO USED | F2: 82 / 3500 | G2: 2026-03-05 | H2: V5.2 tailored | I2: B | J2: 82 | K2: 3500 | L2: 0
A3: EBBR | B3: Brussels Airport | C3: • TRAFFIC: VERY HIGH; MAJOR EU HUB; STRICT SLOT COORDINATION • ATC: COMPLEX TMA WITH HEAVY ARR/DEP FLOWS; SPEED CONTROL COMMON • TAXI: LARGE AIRPORT; MULTIPLE HOT SPOTS AND RWY CROSSINGS • RWY OPS: MULTI-RWY SYSTEM (01/19 – 07R/25L – 07L/25R); CONFIGURATION CHANGES FREQUENT • CURFEW: NIGHT RESTRICTIONS APPLY; CHECK AIP/AOI | D3: • METEO: LOW CEILING / FOG COMMON IN AUTUMN–WINTER • METEO: FREQUENT RAIN / LOW VIS CONDITIONS • WIND: CROSSWIND POSSIBLE DEPENDING RWY CONFIGURATION | E3: • HANDLING: BUSY APRONS; EU INSTITUTION / DIPLOMATIC TRAFFIC COMMON • FUEL: JET A-1 AVAILABLE • NAV: CAT III ILS RWY 25L / 25R; LVP OPERATIONS FREQUENT • INFRA: STRICT NOISE ABATEMENT PROCEDURES | F3: 175 / 3500 | G3: 2026-03-05 | H3: V5.2 tailored | I3: B | J3: 175 | K3: 3500 | L3: 0
A4: EBCI | B4: Brussels South Charleroi Airport | C4: • TRAFFIC: HIGH LCC TRAFFIC; PEAK ARR/DEP BANKS • ATC: SPEED MANAGEMENT COMMON DURING PEAK PERIODS • TAXI: APRON CONGESTION POSSIBLE; FOLLOW MARSHALLER • RWY OPS: RWY 06/24 PRIMARY; BACKTRACK MAY OCCUR • SLOT: STRICT SLOT ADHERENCE REQUIRED | D4: • METEO: LOW CEILING / FOG POSSIBLE IN WINTER • METEO: FREQUENT RAIN / HAZE CONDITIONS • WIND: CROSSWIND POSSIBLE DUE TO SINGLE RWY CONFIGURATION | E4: • SECURITY: STANDARD EU SECURITY PROCEDURES • HANDLING: LIMITED BIZAV INFRASTRUCTURE; PRIOR COORDINATION ADVISED • FUEL: CONFIRM FUELER AVAILABILITY DURING PEAK PERIODS • NAV: ILS AVAILABLE RWY 24; GNSS APPROACH RWY 06 | F4: 614 / 3500 | G4: 2026-03-05 | H4: V5.4 tailored | I4: A | J4: 614 | K4: 3500 | L4: 0
A5: EBLG | B5: Liège Airport | C5: • TRAFFIC: VERY HIGH CARGO TRAFFIC (NIGHT OPERATIONS INTENSE) • ATC: FREIGHT HUB OPS; EXPECT VECTORING / SEQUENCING • TAXI: LARGE CARGO APRONS; FOLLOW MARSHALLER • RWY OPS: RWY 04R/22L PRIMARY; CONFIGURATION MAY CHANGE WITH WIND • RWY OPS: HEAVY AIRCRAFT OPERATIONS COMMON; WAKE TURBULENCE CONSIDERATION | D5: • METEO: LOW CEILING / FOG COMMON IN WINTER • METEO: FREQUENT RAIN / LOW VIS CONDITIONS • WIND: GUSTY CONDITIONS POSSIBLE WITH ATLANTIC WEATHER SYSTEMS | E5: • SECURITY: MAJOR EUROPEAN CARGO HUB; STRICT ACCESS CONTROL • HANDLING: CARGO PRIORITY; BIZAV HANDLING CONFIRMATION ADVISED • FUEL: JET A-1 AVAILABLE; HIGH DEMAND DURING NIGHT CARGO BANKS • NAV: CAT II/III ILS AVAILABLE; LOW VIS OPS COMMON | F5: 659 / 4000 | G5: 2026-03-05 | H5: V5.4 tailored | I5: B | J5: 659 | K5: 4000 | L5: 0
A6: EBOS | B6: Ostend-Bruges International Airport | C6: • TRAFFIC: MODERATE; CARGO AND CHARTER TRAFFIC COMMON • ATC: RELATIVELY LOW COMPLEXITY; MIL ACTIVITY POSSIBLE (COASTAL AREAS) • TAXI: APRON FOLLOW-ME / MARSHALLING COMMON • RWY OPS: RWY 08/26 PRIMARY; SEA BREEZE MAY DRIVE RWY CHANGES • RWY OPS: LONG RWY USED BY HEAVY CARGO AIRCRAFT | D6: • METEO: COASTAL FOG / SEA FOG POSSIBLE • METEO: LOW CLOUD / RAIN FREQUENT WITH NORTH SEA WEATHER • WIND: STRONG AND GUSTY CROSSWINDS COMMON | E6: • SECURITY: STANDARD EU SECURITY PROCEDURES • HANDLING: MODERATE INFRASTRUCTURE; CONFIRM BIZAV SERVICES • FUEL: JET A-1 AVAILABLE; CONFIRM DURING OFF-PEAK HOURS • NAV: ILS RWY 26; COASTAL WEATHER MAY IMPACT APPROACH | F6: 13 / 3000 | G6: 2026-03-05 | H6: V5.4 tailored | I6: A | J6: 13 | K6: 3000 | L6: 0
A7: EDDB | B7: Berlin Brandenburg Airport | C7: • TRAFFIC: HIGH; MAJOR GERMAN HUB; SLOT REQUIRED • ATC: COMPLEX ARRIVAL FLOWS; SPEED CONTROL COMMON • TAXI: LARGE AIRPORT; LONG TAXI TIMES POSSIBLE • RWY OPS: PARALLEL RWY 07L/25R – 07R/25L OPERATIONS • CURFEW: NIGHT RESTRICTIONS APPLY; CHECK AIP/AOI FOR DETAILS | D7: • METEO: WINTER FOG / LOW STRATUS COMMON • METEO: SNOW / ICING CONDITIONS POSSIBLE IN WINTER • WIND: MODERATE CROSSWIND POSSIBLE; EAST WINDS OCCASIONALLY STRONG | E7: • SECURITY: STANDARD EU SECURITY PROCEDURES • HANDLING: BUSY APRONS; FOLLOW-ME / MARSHALLER COMMON • FUEL: JET A-1 AVAILABLE • NAV: CAT II/III ILS AVAILABLE; LOW VIS OPS COMMON | F7: 157 / 3500 | G7: 2026-03-05 | H7: V5.3 tailored | I7: B | J7: 157 | K7: 3500 | L7: 0
A8: EDDC | B8: Dresden Airport | C8: • TRAFFIC: MODERATE; REGIONAL AND CHARTER TRAFFIC • ATC: GENERALLY LOW COMPLEXITY; MIL ACTIVITY POSSIBLE • TAXI: COMPACT AIRPORT; EXPECT MARSHALLER ON APRON • RWY OPS: RWY 04/22 SINGLE RWY OPERATIONS • CURFEW: NIGHT RESTRICTIONS MAY APPLY; CHECK AIP/AOI | D8: • METEO: WINTER FOG / LOW STRATUS POSSIBLE • METEO: SNOW / ICING CONDITIONS POSSIBLE IN WINTER • WIND: CROSSWIND POSSIBLE WITH SINGLE RWY CONFIGURATION | E8: • SECURITY: STANDARD EU SECURITY PROCEDURES • HANDLING: LIMITED BIZAV INFRASTRUCTURE; PRIOR COORDINATION ADVISED • FUEL: JET A-1 AVAILABLE; CONFIRM DURING OFF-PEAK HOURS • NAV: ILS AVAILABLE; LOW VIS OPS POSSIBLE | F8: 755 / 3500 | G8: 2026-03-05 | H8: V5.4 tailored | I8: A | J8: 755 | K8: 3500 | L8: 0
A9: EDDE | B9: Erfurt-Weimar Airport | C9: • TRAFFIC: LOW–MODERATE; CHARTER AND CARGO TRAFFIC • ATC: GENERALLY LOW COMPLEXITY • TAXI: COMPACT AIRPORT; MARSHALLER COMMON ON APRON • RWY OPS: RWY 10/28 SINGLE RWY OPERATIONS • CURFEW: NIGHT RESTRICTIONS MAY APPLY; CHECK AIP/AOI | D9: • METEO: WINTER FOG / LOW STRATUS POSSIBLE • METEO: SNOW / ICING CONDITIONS POSSIBLE IN WINTER • WIND: CROSSWIND POSSIBLE WITH SINGLE RWY CONFIGURATION | E9: • SECURITY: STANDARD EU SECURITY PROCEDURES • HANDLING: LIMITED INFRASTRUCTURE; PRIOR COORDINATION ADVISED • FUEL: JET A-1 AVAILABLE; CONFIRM DURING OFF-PEAK HOURS • NAV: ILS AVAILABLE; LOW VIS OPS POSSIBLE | F9: 1036 / 4000 | G9: 2026-03-05 | H9: V5.4 tailored | I9: A | J9: 1036 | K9: 4000 | L9: 0
A10: EDDF | B10: Frankfurt Airport | C10: • TRAFFIC: EXTREMELY HIGH; MAJOR EUROPEAN HUB; STRICT SLOT ADHERENCE • ATC: COMPLEX MULTI-RWY ARR/DEP SYSTEM; SPEED CONTROL AND HOLDING COMMON • TAXI: VERY LARGE AIRPORT; LONG TAXI TIMES AND COMPLEX ROUTING • RWY OPS: DEP/ARR RWY SEGREGATION (25C/07C MAIN DEP); RWY 18 WEST DEP ONLY • CURFEW: STRICT NIGHT CURFEW; CHECK AIP/AOI | D10: • METEO: RIVER MAIN VALLEY; FOG / LOW STRATUS POSSIBLE • METEO: WINTER SNOW AND DE-ICING OPERATIONS COMMON • WIND: RWY CONFIGURATION CHANGES COMMON WITH WIND | E10: • HANDLING: VERY BUSY APRONS; FOLLOW-ME AND STRICT TAXI ROUTES • FUEL: JET A-1 AVAILABLE; PEAK DEMAND PERIODS • NAV: CAT III ILS OPERATIONS COMMON; LVP PROCEDURES FREQUENT • INFRA: STRICT NOISE ABATEMENT / NIGHT OPS RESTRICTIONS | F10: 364 / 3000 | G10: 2026-03-05 | H10: V5.2 tailored | I10: B | J10: 364 | K10: 3000 | L10: 0
A11: EDDG | B11: Münster Osnabrück Airport | C11: • TRAFFIC: LOW–MODERATE; REGIONAL / CHARTER TRAFFIC • ATC: GENERALLY LOW COMPLEXITY • TAXI: COMPACT AIRPORT; MARSHALLER POSSIBLE ON APRON • RWY OPS: RWY 07/25 SINGLE RWY OPERATIONS • CURFEW: NIGHT RESTRICTIONS MAY APPLY; CHECK AIP/AOI | D11: • METEO: LOW CEILING / FOG POSSIBLE IN WINTER • METEO: RAIN / LOW VIS CONDITIONS POSSIBLE • WIND: CROSSWIND POSSIBLE WITH SINGLE RWY CONFIGURATION | E11: • SECURITY: STANDARD EU SECURITY PROCEDURES • HANDLING: LIMITED INFRASTRUCTURE; PRIOR COORDINATION ADVISED • FUEL: JET A-1 AVAILABLE; CONFIRM DURING OFF-PEAK HOURS • NAV: ILS AVAILABLE; LOW VIS OPS POSSIBLE | F11: 160 / 3000 | G11: 2026-03-05 | H11: V5.4 tailored | I11: A | J11: 160 | K11: 3000 | L11: 0
A12: EDDH | B12: Hamburg Airport | C12: • TRAFFIC: HIGH; BUSY COMMERCIAL AIRPORT CLOSE TO CITY; SLOT COORDINATED • ATC: ARR/DEP FLOWS AFFECTED BY DENSE N GERMANY / NORTH SEA TRAFFIC • TAXI: INTERSECTING RWY LAYOUT; RWY CROSSINGS COMMON • RWY OPS: RWY 05/23 MAIN; RWY 15/33 USED WITH WIND LIMITATIONS • CURFEW: STRICT NIGHT RESTRICTIONS DUE NOISE; CHECK AIP/AOI | D12: • METEO: COASTAL WEATHER INFLUENCE; FOG / LOW STRATUS POSSIBLE • METEO: FREQUENT LOW CEILING AND RAIN • WIND: GUSTY CROSSWINDS POSSIBLE DUE NORTH SEA WEATHER | E12: • HANDLING: BUSY APRON DURING MORNING / EVENING BANKS • FUEL: JET A-1 AVAILABLE • NAV: CAT II/III ILS RWY 23; LOW VISIBILITY OPS POSSIBLE • INFRA: STRICT NOISE ABATEMENT PROCEDURES | F12: 53 / 3000 | G12: 2026-03-05 | H12: V5.3 tailored | I12: B | J12: 53 | K12: 3000 | L12: 0
A13: EDDK | B13: Cologne Bonn Airport | C13: • TRAFFIC: HIGH; MAJOR EUROPEAN CARGO HUB; INTENSE NIGHT CARGO OPERATIONS • ATC: MIXED PASSENGER / HEAVY CARGO TRAFFIC; VECTORING COMMON • TAXI: LARGE AIRPORT; RWY CROSSINGS AND COMPLEX TAXI ROUTING POSSIBLE • RWY OPS: PARALLEL RWY 13L/31R – 13R/31L; FLEXIBLE ARR/DEP USE • CURFEW: NO FULL CURFEW; NIGHT OPERATIONS COMMON (CARGO HUB) | D13: • METEO: RIVER RHINE AREA; FOG / LOW STRATUS POSSIBLE • METEO: FREQUENT LOW CEILING IN AUTUMN / WINTER • WIND: CROSSWIND POSSIBLE DEPENDING RWY CONFIGURATION | E13: • HANDLING: BUSY CARGO APRONS; FREIGHT TRAFFIC PRIORITY POSSIBLE • FUEL: JET A-1 AVAILABLE • NAV: CAT II/III ILS RWY 13L/31R; LOW VIS OPS POSSIBLE • INFRA: SIGNIFICANT NIGHT FREIGHT ACTIVITY | F13: 302 / 3500 | G13: 2026-03-05 | H13: V5.3 tailored | I13: B | J13: 302 | K13: 3500 | L13: 0
... A234: LTCO | B234: Ağrı Airport | C234: • TRAFFIC: VARIABLE INTERNATIONAL TRAFFIC • RWY OPS: CONFIG CHANGES POSSIBLE • TAXI: FOLLOW HOTSPOTS AND ATC INSTRUCTIONS • LATE CLR: POSSIBLE – GO‑AROUND READY • ATC: ACCENTED ENGLISH POSSIBLE | D234: • METEO: LOCAL WEATHER HAZARDS (HEAT / DUST / LOW VIS) • WIND: GUSTS POSSIBLE | E234: • HANDLING: CONFIRM FUEL / GROUND SUPPORT • SECURITY: CHECK CURRENT STATE RISK LEVEL • NAV: VERIFY NAVAID STATUS | F234: 5462 / 11000 | G234: 2026-03-05 | H234: V5 FINAL tailored | I234: B | J234: 5462 | K234: 11000 | L234: 1
A235: LTCP | B235: Adıyaman Airport | C235: • TRAFFIC: VARIABLE INTERNATIONAL TRAFFIC • RWY OPS: CONFIG CHANGES POSSIBLE • TAXI: FOLLOW HOTSPOTS AND ATC INSTRUCTIONS • LATE CLR: POSSIBLE – GO‑AROUND READY • ATC: ACCENTED ENGLISH POSSIBLE | D235: • METEO: LOCAL WEATHER HAZARDS (HEAT / DUST / LOW VIS) • WIND: GUSTS POSSIBLE | E235: • HANDLING: CONFIRM FUEL / GROUND SUPPORT • SECURITY: CHECK CURRENT STATE RISK LEVEL • NAV: VERIFY NAVAID STATUS | F235: 2216 / 7000 | G235: 2026-03-05 | I235: A | J235: 2201 | K235: 3500 | L235: 0
A236: LTCR | B236: Kahramanmaraş Airport | C236: • TRAFFIC: VARIABLE INTERNATIONAL TRAFFIC • RWY OPS: CONFIG CHANGES POSSIBLE • TAXI: FOLLOW HOTSPOTS AND ATC INSTRUCTIONS • LATE CLR: POSSIBLE – GO‑AROUND READY • ATC: ACCENTED ENGLISH POSSIBLE | D236: • METEO: LOCAL WEATHER HAZARDS (HEAT / DUST / LOW VIS) • WIND: GUSTS POSSIBLE | E236: • HANDLING: CONFIRM FUEL / GROUND SUPPORT • SECURITY: CHECK CURRENT STATE RISK LEVEL • NAV: VERIFY NAVAID STATUS | F236: 1729 / 6500 | G236: 2026-03-05 | H236: V5 FINAL tailored | I236: B | J236: 1729 | K236: 6500 | L236: 0
A237: LTCS | B237: Şanlıurfa GAP Airport | C237: • TRAFFIC: VARIABLE INTERNATIONAL TRAFFIC • RWY OPS: CONFIG CHANGES POSSIBLE • TAXI: FOLLOW HOTSPOTS AND ATC INSTRUCTIONS • LATE CLR: POSSIBLE – GO‑AROUND READY • ATC: ACCENTED ENGLISH POSSIBLE | D237: • METEO: LOCAL WEATHER HAZARDS (HEAT / DUST / LOW VIS) • WIND: GUSTS POSSIBLE | E237: • HANDLING: CONFIRM FUEL / GROUND SUPPORT • SECURITY: CHECK CURRENT STATE RISK LEVEL • NAV: VERIFY NAVAID STATUS | F237: 2708 / 7500 | G237: 2026-03-05 | H237: V5 FINAL tailored | I237: B | J237: 2708 | K237: 7500 | L237: 0
A238: LTCT | B238: Hatay Airport | C238: • TRAFFIC: VARIABLE INTERNATIONAL TRAFFIC • RWY OPS: CONFIG CHANGES POSSIBLE • TAXI: FOLLOW HOTSPOTS AND ATC INSTRUCTIONS • LATE CLR: POSSIBLE – GO‑AROUND READY • ATC: ACCENTED ENGLISH POSSIBLE | D238: • METEO: LOCAL WEATHER HAZARDS (HEAT / DUST / LOW VIS) • WIND: GUSTS POSSIBLE | E238: • HANDLING: CONFIRM FUEL / GROUND SUPPORT • SECURITY: CHECK CURRENT STATE RISK LEVEL • NAV: VERIFY NAVAID STATUS | F238: 3101 / 8000 | G238: 2026-03-05 | H238: V5 FINAL tailored | I238: B | J238: 3101 | K238: 8000 | L238: 0
A239: LTCU | B239: Şırnak Şerafettin Elçi Airport | C239: • TRAFFIC: VARIABLE INTERNATIONAL TRAFFIC • RWY OPS: CONFIG CHANGES POSSIBLE • TAXI: FOLLOW HOTSPOTS AND ATC INSTRUCTIONS • LATE CLR: POSSIBLE – GO‑AROUND READY • ATC: ACCENTED ENGLISH POSSIBLE | D239: • METEO: LOCAL WEATHER HAZARDS (HEAT / DUST / LOW VIS) • WIND: GUSTS POSSIBLE | E239: • HANDLING: CONFIRM FUEL / GROUND SUPPORT • SECURITY: CHECK CURRENT STATE RISK LEVEL • NAV: VERIFY NAVAID STATUS | F239: 3506 / 8500 | G239: 2026-03-05 | H239: V5 FINAL tailored | I239: B | J239: 3506 | K239: 8500 | L239: 0
A240: LTCV | B240: Siirt Airport | C240: • TRAFFIC: VARIABLE INTERNATIONAL TRAFFIC • RWY OPS: CONFIG CHANGES POSSIBLE • TAXI: FOLLOW HOTSPOTS AND ATC INSTRUCTIONS • LATE CLR: POSSIBLE – GO‑AROUND READY • ATC: ACCENTED ENGLISH POSSIBLE | D240: • METEO: LOCAL WEATHER HAZARDS (HEAT / DUST / LOW VIS) • WIND: GUSTS POSSIBLE | E240: • HANDLING: CONFIRM FUEL / GROUND SUPPORT • SECURITY: CHECK CURRENT STATE RISK LEVEL • NAV: VERIFY NAVAID STATUS | F240: 2038 / 7000 | G240: 2026-03-05 | H240: V5 FINAL tailored | I240: B | J240: 2038 | K240: 7000 | L240: 0
A241: LTDB | B241: Çukurova International Airport | C241: • OPS: NEWER FIELD—PROCEDURES/LOCAL PRACTICE MAY EVOLVE; BRIEF CURRENT AIP/NOTAM • TRAFFIC: VARIABLE; EXPECT PROCEDURAL ATC • TAXI: WATCH SIGNAGE/STOPBARS; RUNWAY INCURSION PREVENTION • RWY OPS: WORKS/CLOSED TWYS POSSIBLE; NOTAM-DRIVEN • LATE CLR: EXPEDITE OPS MAY OCCUR AT PEAKS | D241: • METEO: HEAT + TSRA; VIS/CB AVOIDANCE • OBSTACLES: CONSTRUCTION/CRANES—NOTAM ESSENTIAL | E241: • SECURITY: REGIONAL SITUATION VARIABLE; CHECK UPDATES • HANDLING: CONFIRM FUEL/HANDLING HOURS/CAPACITY • NAV: VERIFY NAVAID STATUS; GNSS INTERFERENCE POSSIBLE | F241: 35 / 3500 | G241: 2026-03-05 | H241: V5.2 tailored | I241: B | J241: 35 | K241: 3500 | L241: 0
A242: LTFD | B242: Balıkesir Koca Seyit Airport | C242: • TRAFFIC: VARIABLE INTERNATIONAL TRAFFIC • RWY OPS: CONFIG CHANGES POSSIBLE • TAXI: FOLLOW HOTSPOTS AND ATC INSTRUCTIONS • LATE CLR: POSSIBLE – GO‑AROUND READY • ATC: ACCENTED ENGLISH POSSIBLE | D242: • METEO: LOCAL WEATHER HAZARDS (HEAT / DUST / LOW VIS) • WIND: GUSTS POSSIBLE | E242: • HANDLING: CONFIRM FUEL / GROUND SUPPORT • SECURITY: CHECK CURRENT STATE RISK LEVEL • NAV: VERIFY NAVAID STATUS | F242: 50 / 3500 | G242: 2026-03-05 | H242: V5 FINAL tailored | I242: B | J242: 50 | K242: 3500 | L242: 0
A243: LTFE | B243: Bodrum Milas Airport | C243: • TRAFFIC: BODRUM MAJOR TOURISM AIRPORT WITH HEAVY SUMMER TRAFFIC • RWY OPS: PARALLEL RWYS 10L/28R - 10R/28L • TAXI: LARGE TERMINAL APRON COMPLEX • ATC: HIGH ARRIVAL FLOW DURING SUMMER • LATE CLR: DEPARTURES HELD DURING ARRIVAL STREAMS | D243: • METEO: AEGEAN WIND EVENTS AND SUMMER HAZE • CONTAMINATION: WET RWY DURING HEAVY RAIN | E243: • SECURITY: HIGH SECURITY • HANDLING: LARGE TERMINAL APRON • NAV: RWY 28R ILS 3.9° | F243: 21 / 3000 | G243: 2026-03-16 | H243: V5.2 tailored | I243: B | J243: 21 | K243: 3000 | L243: 0
A244: LTFG | B244: Gazipaşa-Alanya Airport | C244: • TRAFFIC: VARIABLE INTERNATIONAL TRAFFIC • RWY OPS: APP RW08 / DEPT RW26 ONLY • TAXI: FOLLOW HOTSPOTS AND ATC INSTRUCTIONS • LATE CLR: POSSIBLE – GO‑AROUND READY • ATC: ACCENTED ENGLISH POSSIBLE | D244: • METEO: LOCAL WEATHER HAZARDS (HEAT / DUST / LOW VIS) • WIND: GUSTS POSSIBLE / MAY NEED SPECIAL TRAINING FOR BULK LANDING PROCEDURE (CHECK TAIL WIND COMPONENT FOR APP/TO PERFORMANCE) | E244: • HANDLING: CONFIRM FUEL / GROUND SUPPORT • SECURITY: CHECK CURRENT STATE RISK LEVEL • NAV: VERIFY NAVAID STATUS / CHECK GNSS ACCURACY | F244: 92 / 3500 | G244: 2026-03-05 | H244: V5 FINAL tailored | I244: A | J244: 92 | K244: 3500 | L244: 0
A245: LTFH | B245: Samsun-Çarşamba Airport | C245: • TRAFFIC: VARIABLE INTERNATIONAL TRAFFIC • RWY OPS: CONFIG CHANGES POSSIBLE • TAXI: FOLLOW HOTSPOTS AND ATC INSTRUCTIONS • LATE CLR: POSSIBLE – GO‑AROUND READY • ATC: ACCENTED ENGLISH POSSIBLE | D245: • METEO: LOCAL WEATHER HAZARDS (HEAT / DUST / LOW VIS) • WIND: GUSTS POSSIBLE | E245: • HANDLING: CONFIRM FUEL / GROUND SUPPORT • SECURITY: CHECK CURRENT STATE RISK LEVEL • NAV: VERIFY NAVAID STATUS | F245: 18 / 3500 | G245: 2026-03-05 | H245: V5 FINAL tailored | I245: B | J245: 18 | K245: 3500 | L245: 0
A246: LTFJ | B246: Istanbul Sabiha Gökçen Airport | C246: • TRAFFIC: VARIABLE INTERNATIONAL TRAFFIC • RWY OPS: CONFIG CHANGES POSSIBLE • TAXI: FOLLOW HOTSPOTS AND ATC INSTRUCTIONS • LATE CLR: POSSIBLE – GO‑AROUND READY • ATC: ACCENTED ENGLISH POSSIBLE | D246: • METEO: LOCAL WEATHER HAZARDS (HEAT / DUST / LOW VIS) • WIND: GUSTS POSSIBLE | E246: • HANDLING: CONFIRM FUEL / GROUND SUPPORT • SECURITY: CHECK CURRENT STATE RISK LEVEL • NAV: VERIFY NAVAID STATUS | F246: 312 / 3500 | G246: 2026-03-05 | H246: V5 FINAL tailored | I246: B | J246: 312 | K246: 3500 | L246: 0
A247: LTFM | B247: Istanbul Airport | C247: • TRAFFIC: VARIABLE INTERNATIONAL TRAFFIC • RWY OPS: CONFIG CHANGES POSSIBLE • TAXI: FOLLOW HOTSPOTS AND ATC INSTRUCTIONS • LATE CLR: POSSIBLE – GO‑AROUND READY • ATC: ACCENTED ENGLISH POSSIBLE | D247: • METEO: LOCAL WEATHER HAZARDS (HEAT / DUST / LOW VIS) • WIND: GUSTS POSSIBLE | E247: • HANDLING: CONFIRM FUEL / GROUND SUPPORT • SECURITY: CHECK CURRENT STATE RISK LEVEL • NAV: VERIFY NAVAID STATUS | F247: 325 / 3000 | G247: 2026-03-05 | H247: V5 FINAL tailored | I247: B | J247: 325 | K247: 3000 | L247: 0
... A566: UAKD | B566: Zhezkazgan Airport | C566: • TRAFFIC: LOW; DOMESTIC REGIONAL • RWY OPS: SINGLE RWY; CHECK ACTIVE CONFIG • TAXI: COMPACT APRON | D566: • METEO: STEPPE CLIMATE; EXTREME TEMPERATURES • WIND: STRONG WINDS POSSIBLE | E566: • HANDLING: LIMITED; CONFIRM PRE-ARRIVAL • FUEL: CONFIRM AVAILABILITY | F566: 1188 / 3000 | G566: 2026-03-05 | H566: V5 FINAL tailored | I566: A | J566: 1188 | K566: 3000 | L566: 0

Sheet PPS
A1: ICAO INPUT | B1: ltcg
A3: PPS BRIEFING OUTPUT (COPY/PASTE) | B3: =IF($B$1="","",UPPER(TRIM($B$1)) & " PPS BRIEFING" & CHAR(10) & CHAR(10) & $B$11 & CHAR(10) & CHAR(10) & "SECTION 1" & CHAR(10) & $B$5 & CHAR(10) & CHAR(10) & "SECTION 2" & CHAR(10) & $B$7 & CHAR(10) & CHAR(10) & "SECTION 3" & CHAR(10) & $B$9) -> LTCG PPS BRIEFING AERODROME RISK LEVEL: LOW (CAT B) | DISPATCH OK | MITIGATION: STRICT TERRAIN/OBSTACLE PROC COMPLIANCE; REVIEW MSA / MISSED APCH / CHECK TAF/METAR/NOTAM; CONTAMINATION / DE-ICE PLAN SECTION 1 • TRAFFIC: TRABZON MAJOR BLACK SEA AIRPORT WITH HIGH DOMESTIC TRAFFIC • RWY OPS: SINGLE RWY 11/29 • TAXI: LARGE APRON COMPLEX • ATC: ARRIVAL FLOW BUILDS DURING SUMMER AND HOLIDAY PERIODS • LATE CLR: DEPARTURES HELD DURING ARRIVAL STREAMS SECTION 2 • METEO: BLACK SEA LOW CLOUD AND STRONG WIND EVENTS • CONTAMINATION: WET RWY DURING HEAVY RAIN SECTION 3 • SECURITY: HIGH SECURITY • HANDLING: LARGE TERMINAL APRON • NAV: RWY 11 ILS 3.3° / RWY 29 LOC ~3.3°
A5: SECTION 1 | B5: =IFERROR(VLOOKUP($B$1,AIRPORT_DB!$A:$E,3,FALSE()),"ICAO NOT FOUND") -> • TRAFFIC: TRABZON MAJOR BLACK SEA AIRPORT WITH HIGH DOMESTIC TRAFFIC • RWY OPS: SINGLE RWY 11/29 • TAXI: LARGE APRON COMPLEX • ATC: ARRIVAL FLOW BUILDS DURING SUMMER AND HOLIDAY PERIODS • LATE CLR: DEPARTURES HELD DURING ARRIVAL STREAMS
A7: SECTION 2 | B7: =IFERROR(VLOOKUP($B$1,AIRPORT_DB!$A:$E,4,FALSE()),"") -> • METEO: BLACK SEA LOW CLOUD AND STRONG WIND EVENTS • CONTAMINATION: WET RWY DURING HEAVY RAIN
A9: SECTION 3 | B9: =IFERROR(VLOOKUP($B$1,AIRPORT_DB!$A:$E,5,FALSE()),"") -> • SECURITY: HIGH SECURITY • HANDLING: LARGE TERMINAL APRON • NAV: RWY 11 ILS 3.3° / RWY 29 LOC ~3.3°
A11: RISK LEVEL LINE (AUTO – MATRIX_V8 + CATEGORY) | B11: =IF($B$1="","","AERODROME RISK LEVEL: " & IF(MATRIX_V8!F2="","N/A",MATRIX_V8!F2) & " (CAT " & IF(MATRIX_V8!H2="","N/A",MATRIX_V8!H2) & ")" & " | " & IF(MATRIX_V8!G2="","REVIEW REQUIRED",MATRIX_V8!G2) & IF(MATRIX_V8!I2<>""," | MITIGATION: " & MATRIX_V8!I2,"")) -> AERODROME RISK LEVEL: LOW (CAT B) | DISPATCH OK | MITIGATION: STRICT TERRAIN/OBSTACLE PROC COMPLIANCE; REVIEW MSA / MISSED APCH / CHECK TAF/METAR/NOTAM; CONTAMINATION / DE-ICE PLAN
A14: RISK SUMMARY (AUTO – MATRIX_V8)
A15: =IF(PPS!B1="","","AERODROME RISK LEVEL: " & MATRIX_V8!F2 & " | " & MATRIX_V8!G2 & IF(MATRIX_V8!I2<>""," | MITIGATION: " & MATRIX_V8!I2,"")) -> AERODROME RISK LEVEL: LOW | DISPATCH OK | MITIGATION: STRICT TERRAIN/OBSTACLE PROC COMPLIANCE; REVIEW MSA / MISSED APCH / CHECK TAF/METAR/NOTAM; CONTAMINATION / DE-ICE PLAN

Sheet MATRIX_STORE
A1: ICAO | B1: S_1 | C1: S_2 | D1: S_3 | E1: S_4 | F1: S_5 | G1: S_6 | H1: S_7 | I1: S_8 | J1: S_9 | K1: S_10_AD_ELEV_MSA | L1: L_1 | M1: L_2 | N1: L_3 | O1: L_4 | P1: L_5 | Q1: L_6 | R1: L_7 | S1: L_8 | T1: L_9 | U1: L_10_AD_ELEV_MSA | V1: MAX_SCORE | W1: RISK_LEVEL | X1: OPS_APPROVAL | Y1: MITIGATION | Z1: Updated_By | AA1: Updated_On | AB1: CATEGORY | AC1: MAX_SEVERITY | AD1: MAX_LIKELIHOOD | AE1: LEGACY_S10 | AF1: LEGACY_L10
A2: DAAG | B2: 2 | C2: 2 | D2: 4 | E2: 4 | F2: 2 | G2: 3 | H2: 2 | I2: 4 | J2: 4 | K2: =IFERROR(INDEX(AIRPORT_DB!$L:$L,MATCH($A2,AIRPORT_DB!$A:$A,0))+1,2) -> 1 | L2: 2 | M2: 2 | N2: 3 | O2: 3 | P2: 2 | Q2: 2 | R2: 2 | S2: 3 | T2: 3 | U2: =IFERROR(INDEX(AIRPORT_DB!$L:$L,MATCH($A2,AIRPORT_DB!$A:$A,0))+1,2) -> 1 | V2: =ROUND(AVERAGE(LARGE(B2:K2,{1,2,3}))+AVERAGE(LARGE(L2:U2,{1,2,3}))-1,0)+IF(INDEX(AIRPORT_DB!$L:$L,MATCH($A2,AIRPORT_DB!$A:$A,0))>=1,1,0)+IF(AB2="C",1,0) -> 6 | W2: =IF(V2<=6,"LOW",IF(V2<=9,"MEDIUM",IF(V2<=12,"HIGH","EXTREME"))) -> LOW | X2: =IF(W2="EXTREME","OPS MANAGER APPROVAL REQUIRED",IF(AND(W2="HIGH",AB2="C"),"OPS MANAGER APPROVAL REQUIRED",IF(W2="HIGH","CAPTAIN REVIEW / DISPATCH COORDINATION","DISPATCH OK"))) -> DISPATCH OK | Y2: CHECK TAF/METAR/NOTAM; CONTAMINATION / DE-ICE PLAN / STERILE COMMS; FULL READBACK / QUERY IF DOUBT | Z2: OpenAI - V9 setup | AA2: 2026-03-08 | AB2: B | AC2: =ROUND(AVERAGE(LARGE(B2:K2,{1,2,3})),0) -> 4 | AD2: =ROUND(AVERAGE(LARGE(L2:U2,{1,2,3})),0) -> 3 | AE2: 2 | AF2: 2
A3: EBBR | B3: 3 | C3: 4 | D3: 2 | E3: 4 | F3: 3 | G3: 3 | H3: 2 | I3: 3 | J3: 4 | K3: =IFERROR(INDEX(AIRPORT_DB!$L:$L,MATCH($A3,AIRPORT_DB!$A:$A,0))+1,2) -> 1 | L3: 2 | M3: 3 | N3: 2 | O3: 3 | P3: 2 | Q3: 2 | R3: 2 | S3: 2 | T3: 3 | U3: =IFERROR(INDEX(AIRPORT_DB!$L:$L,MATCH($A3,AIRPORT_DB!$A:$A,0))+1,2) -> 1 | V3: =ROUND(AVERAGE(LARGE(B3:K3,{1,2,3}))+AVERAGE(LARGE(L3:U3,{1,2,3}))-1,0)+IF(INDEX(AIRPORT_DB!$L:$L,MATCH($A3,AIRPORT_DB!$A:$A,0))>=1,1,0)+IF(AB3="C",1,0) -> 6 | W3: =IF(V3<=6,"LOW",IF(V3<=9,"MEDIUM",IF(V3<=12,"HIGH","EXTREME"))) -> LOW | X3: =IF(W3="EXTREME","OPS MANAGER APPROVAL REQUIRED",IF(AND(W3="HIGH",AB3="C"),"OPS MANAGER APPROVAL REQUIRED",IF(W3="HIGH","CAPTAIN REVIEW / DISPATCH COORDINATION","DISPATCH OK"))) -> DISPATCH OK | Y3: STRICT TERRAIN/OBSTACLE PROC COMPLIANCE; REVIEW MSA / MISSED APCH / STERILE COMMS; FULL READBACK / QUERY IF DOUBT | Z3: OpenAI - V9 setup | AA3: 2026-03-08 | AB3: B | AC3: =ROUND(AVERAGE(LARGE(B3:K3,{1,2,3})),0) -> 4 | AD3: =ROUND(AVERAGE(LARGE(L3:U3,{1,2,3})),0) -> 3 | AE3: 3 | AF3: 2
A4: EBCI | B4: 3 | C4: 4 | D4: 2 | E4: 4 | F4: 3 | G4: 3 | H4: 2 | I4: 3 | J4: 3 | K4: =IFERROR(INDEX(AIRPORT_DB!$L:$L,MATCH($A4,AIRPORT_DB!$A:$A,0))+1,2) -> 1 | L4: 2 | M4: 3 | N4: 2 | O4: 3 | P4: 2 | Q4: 2 | R4: 2 | S4: 2 | T4: 2 | U4: =IFERROR(INDEX(AIRPORT_DB!$L:$L,MATCH($A4,AIRPORT_DB!$A:$A,0))+1,2) -> 1 | V4: =ROUND(AVERAGE(LARGE(B4:K4,{1,2,3}))+AVERAGE(LARGE(L4:U4,{1,2,3}))-1,0)+IF(INDEX(AIRPORT_DB!$L:$L,MATCH($A4,AIRPORT_DB!$A:$A,0))>=1,1,0)+IF(AB4="C",1,0) -> 5 | W4: =IF(V4<=6,"LOW",IF(V4<=9,"MEDIUM",IF(V4<=12,"HIGH","EXTREME"))) -> LOW | X4: =IF(W4="EXTREME","OPS MANAGER APPROVAL REQUIRED",IF(AND(W4="HIGH",AB4="C"),"OPS MANAGER APPROVAL REQUIRED",IF(W4="HIGH","CAPTAIN REVIEW / DISPATCH COORDINATION","DISPATCH OK"))) -> DISPATCH OK | Y4: STRICT TERRAIN/OBSTACLE PROC COMPLIANCE; REVIEW MSA / MISSED APCH / STERILE COMMS; FULL READBACK / QUERY IF DOUBT | Z4: OpenAI - V9 setup | AA4: 2026-03-08 | AB4: A | AC4: =ROUND(AVERAGE(LARGE(B4:K4,{1,2,3})),0) -> 4 | AD4: =ROUND(AVERAGE(LARGE(L4:U4,{1,2,3})),0) -> 3 | AE4: 3 | AF4: 2
A5: EBLG | B5: 3 | C5: 4 | D5: 2 | E5: 4 | F5: 3 | G5: 3 | H5: 2 | I5: 3 | J5: 4 | K5: =IFERROR(INDEX(AIRPORT_DB!$L:$L,MATCH($A5,AIRPORT_DB!$A:$A,0))+1,2) -> 1 | L5: 2 | M5: 3 | N5: 2 | O5: 3 | P5: 2 | Q5: 2 | R5: 2 | S5: 2 | T5: 3 | U5: =IFERROR(INDEX(AIRPORT_DB!$L:$L,MATCH($A5,AIRPORT_DB!$A:$A,0))+1,2) -> 1 | V5: =ROUND(AVERAGE(LARGE(B5:K5,{1,2,3}))+AVERAGE(LARGE(L5:U5,{1,2,3}))-1,0)+IF(INDEX(AIRPORT_DB!$L:$L,MATCH($A5,AIRPORT_DB!$A:$A,0))>=1,1,0)+IF(AB5="C",1,0) -> 6 | W5: =IF(V5<=6,"LOW",IF(V5<=9,"MEDIUM",IF(V5<=12,"HIGH","EXTREME"))) -> LOW | X5: =IF(W5="EXTREME","OPS MANAGER APPROVAL REQUIRED",IF(AND(W5="HIGH",AB5="C"),"OPS MANAGER APPROVAL REQUIRED",IF(W5="HIGH","CAPTAIN REVIEW / DISPATCH COORDINATION","DISPATCH OK"))) -> DISPATCH OK | Y5: STRICT TERRAIN/OBSTACLE PROC COMPLIANCE; REVIEW MSA / MISSED APCH / STERILE COMMS; FULL READBACK / QUERY IF DOUBT | Z5: OpenAI - V9 setup | AA5: 2026-03-08 | AB5: B | AC5: =ROUND(AVERAGE(LARGE(B5:K5,{1,2,3})),0) -> 4 | AD5: =ROUND(AVERAGE(LARGE(L5:U5,{1,2,3})),0) -> 3 | AE5: 3 | AF5: 2
A6: EBOS | B6: 3 | C6: 4 | D6: 2 | E6: 4 | F6: 3 | G6: 3 | H6: 2 | I6: 3 | J6: 3 | K6: =IFERROR(INDEX(AIRPORT_DB!$L:$L,MATCH($A6,AIRPORT_DB!$A:$A,0))+1,2) -> 1 | L6: 2 | M6: 3 | N6: 2 | O6: 3 | P6: 2 | Q6: 2 | R6: 2 | S6: 2 | T6: 2 | U6: =IFERROR(INDEX(AIRPORT_DB!$L:$L,MATCH($A6,AIRPORT_DB!$A:$A,0))+1,2) -> 1 | V6: =ROUND(AVERAGE(LARGE(B6:K6,{1,2,3}))+AVERAGE(LARGE(L6:U6,{1,2,3}))-1,0)+IF(INDEX(AIRPORT_DB!$L:$L,MATCH($A6,AIRPORT_DB!$A:$A,0))>=1,1,0)+IF(AB6="C",1,0) -> 5 | W6: =IF(V6<=6,"LOW",IF(V6<=9,"MEDIUM",IF(V6<=12,"HIGH","EXTREME"))) -> LOW | X6: =IF(W6="EXTREME","OPS MANAGER APPROVAL REQUIRED",IF(AND(W6="HIGH",AB6="C"),"OPS MANAGER APPROVAL REQUIRED",IF(W6="HIGH","CAPTAIN REVIEW / DISPATCH COORDINATION","DISPATCH OK"))) -> DISPATCH OK | Y6: STRICT TERRAIN/OBSTACLE PROC COMPLIANCE; REVIEW MSA / MISSED APCH / STERILE COMMS; FULL READBACK / QUERY IF DOUBT | Z6: OpenAI - V9 setup | AA6: 2026-03-08 | AB6: A | AC6: =ROUND(AVERAGE(LARGE(B6:K6,{1,2,3})),0) -> 4 | AD6: =ROUND(AVERAGE(LARGE(L6:U6,{1,2,3})),0) -> 3 | AE6: 2 | AF6: 2
A7: EDDB | B7: 4 | C7: 4 | D7: 4 | E7: 4 | F7: 4 | G7: 3 | H7: 2 | I7: 3 | J7: 4 | K7: =IFERROR(INDEX(AIRPORT_DB!$L:$L,MATCH($A7,AIRPORT_DB!$A:$A,0))+1,2) -> 1 | L7: 4 | M7: 3 | N7: 3 | O7: 3 | P7: 3 | Q7: 2 | R7: 2 | S7: 2 | T7: 3 | U7: =IFERROR(INDEX(AIRPORT_DB!$L:$L,MATCH($A7,AIRPORT_DB!$A:$A,0))+1,2) -> 1 | V7: =ROUND(AVERAGE(LARGE(B7:K7,{1,2,3}))+AVERAGE(LARGE(L7:U7,{1,2,3}))-1,0)+IF(INDEX(AIRPORT_DB!$L:$L,MATCH($A7,AIRPORT_DB!$A:$A,0))>=1,1,0)+IF(AB7="C",1,0) -> 6 | W7: =IF(V7<=6,"LOW",IF(V7<=9,"MEDIUM",IF(V7<=12,"HIGH","EXTREME"))) -> LOW | X7: =IF(W7="EXTREME","OPS MANAGER APPROVAL REQUIRED",IF(AND(W7="HIGH",AB7="C"),"OPS MANAGER APPROVAL REQUIRED",IF(W7="HIGH","CAPTAIN REVIEW / DISPATCH COORDINATION","DISPATCH OK"))) -> DISPATCH OK | Y7: BRIEF APP/TRAFFIC FLOW; STABILIZED APPROACH / GO-AROUND READY | Z7: OpenAI - V9 setup | AA7: 2026-03-08 | AB7: B | AC7: =ROUND(AVERAGE(LARGE(B7:K7,{1,2,3})),0) -> 4 | AD7: =ROUND(AVERAGE(LARGE(L7:U7,{1,2,3})),0) -> 3 | AE7: 3 | AF7: 2
A8: EDDC | B8: 3 | C8: 4 | D8: 4 | E8: 4 | F8: 3 | G8: 3 | H8: 2 | I8: 3 | J8: 4 | K8: =IFERROR(INDEX(AIRPORT_DB!$L:$L,MATCH($A8,AIRPORT_DB!$A:$A,0))+1,2) -> 1 | L8: 2 | M8: 3 | N8: 3 | O8: 3 | P8: 2 | Q8: 2 | R8: 2 | S8: 2 | T8: 3 | U8: =IFERROR(INDEX(AIRPORT_DB!$L:$L,MATCH($A8,AIRPORT_DB!$A:$A,0))+1,2) -> 1 | V8: =ROUND(AVERAGE(LARGE(B8:K8,{1,2,3}))+AVERAGE(LARGE(L8:U8,{1,2,3}))-1,0)+IF(INDEX(AIRPORT_DB!$L:$L,MATCH($A8,AIRPORT_DB!$A:$A,0))>=1,1,0)+IF(AB8="C",1,0) -> 6 | W8: =IF(V8<=6,"LOW",IF(V8<=9,"MEDIUM",IF(V8<=12,"HIGH","EXTREME"))) -> LOW | X8: =IF(W8="EXTREME","OPS MANAGER APPROVAL REQUIRED",IF(AND(W8="HIGH",AB8="C"),"OPS MANAGER APPROVAL REQUIRED",IF(W8="HIGH","CAPTAIN REVIEW / DISPATCH COORDINATION","DISPATCH OK"))) -> DISPATCH OK | Y8: STRICT TERRAIN/OBSTACLE PROC COMPLIANCE; REVIEW MSA / MISSED APCH / CHECK TAF/METAR/NOTAM; CONTAMINATION / DE-ICE PLAN | Z8: OpenAI - V9 setup | AA8: 2026-03-08 | AB8: A | AC8: =ROUND(AVERAGE(LARGE(B8:K8,{1,2,3})),0) -> 4 | AD8: =ROUND(AVERAGE(LARGE(L8:U8,{1,2,3})),0) -> 3 | AE8: 3 | AF8: 2
A9: EDDE | B9: 3 | C9: 4 | D9: 4 | E9: 4 | F9: 3 | G9: 3 | H9: 2 | I9: 3 | J9: 3 | K9: =IFERROR(INDEX(AIRPORT_DB!$L:$L,MATCH($A9,AIRPORT_DB!$A:$A,0))+1,2) -> 1 | L9: 2 | M9: 3 | N9: 3 | O9: 3 | P9: 2 | Q9: 2 | R9: 2 | S9: 2 | T9: 2 | U9: =IFERROR(INDEX(AIRPORT_DB!$L:$L,MATCH($A9,AIRPORT_DB!$A:$A,0))+1,2) -> 1 | V9: =ROUND(AVERAGE(LARGE(B9:K9,{1,2,3}))+AVERAGE(LARGE(L9:U9,{1,2,3}))-1,0)+IF(INDEX(AIRPORT_DB!$L:$L,MATCH($A9,AIRPORT_DB!$A:$A,0))>=1,1,0)+IF(AB9="C",1,0) -> 6 | W9: =IF(V9<=6,"LOW",IF(V9<=9,"MEDIUM",IF(V9<=12,"HIGH","EXTREME"))) -> LOW | X9: =IF(W9="EXTREME","OPS MANAGER APPROVAL REQUIRED",IF(AND(W9="HIGH",AB9="C"),"OPS MANAGER APPROVAL REQUIRED",IF(W9="HIGH","CAPTAIN REVIEW / DISPATCH COORDINATION","DISPATCH OK"))) -> DISPATCH OK | Y9: STRICT TERRAIN/OBSTACLE PROC COMPLIANCE; REVIEW MSA / MISSED APCH / CHECK TAF/METAR/NOTAM; CONTAMINATION / DE-ICE PLAN | Z9: OpenAI - V9 setup | AA9: 2026-03-08 | AB9: A | AC9: =ROUND(AVERAGE(LARGE(B9:K9,{1,2,3})),0) -> 4 | AD9: =ROUND(AVERAGE(LARGE(L9:U9,{1,2,3})),0) -> 3 | AE9: 3 | AF9: 2
A10: EDDF | B10: 4 | C10: 4 | D10: 4 | E10: 4 | F10: 4 | G10: 4 | H10: 2 | I10: 2 | J10: 2 | K10: =IFERROR(INDEX(AIRPORT_DB!$L:$L,MATCH($A10,AIRPORT_DB!$A:$A,0))+1,2) -> 1 | L10: 4 | M10: 3 | N10: 3 | O10: 3 | P10: 3 | Q10: 4 | R10: 2 | S10: 2 | T10: 2 | U10: =IFERROR(INDEX(AIRPORT_DB!$L:$L,MATCH($A10,AIRPORT_DB!$A:$A,0))+1,2) -> 1 | V10: =ROUND(AVERAGE(LARGE(B10:K10,{1,2,3}))+AVERAGE(LARGE(L10:U10,{1,2,3}))-1,0)+IF(INDEX(AIRPORT_DB!$L:$L,MATCH($A10,AIRPORT_DB!$A:$A,0))>=1,1,0)+IF(AB10="C",1,0) -> 7 | W10: =IF(V10<=6,"LOW",IF(V10<=9,"MEDIUM",IF(V10<=12,"HIGH","EXTREME"))) -> MEDIUM | X10: =IF(W10="EXTREME","OPS MANAGER APPROVAL REQUIRED",IF(AND(W10="HIGH",AB10="C"),"OPS MANAGER APPROVAL REQUIRED",IF(W10="HIGH","CAPTAIN REVIEW / DISPATCH COORDINATION","DISPATCH OK"))) -> DISPATCH OK | Y10: BRIEF APP/TRAFFIC FLOW; STABILIZED APPROACH / GO-AROUND READY / STRICT RWY IDENTIFICATION; LATE CLR / GO-AROUND BRIEF | Z10: OpenAI - V9 setup | AA10: 2026-03-08 | AB10: B | AC10: =ROUND(AVERAGE(LARGE(B10:K10,{1,2,3})),0) -> 4 | AD10: =ROUND(AVERAGE(LARGE(L10:U10,{1,2,3})),0) -> 4 | AE10: 2 | AF10: 2
A11: EDDG | B11: 3 | C11: 4 | D11: 4 | E11: 4 | F11: 3 | G11: 3 | H11: 2 | I11: 3 | J11: 3 | K11: =IFERROR(INDEX(AIRPORT_DB!$L:$L,MATCH($A11,AIRPORT_DB!$A:$A,0))+1,2) -> 1 | L11: 2 | M11: 3 | N11: 3 | O11: 3 | P11: 2 | Q11: 2 | R11: 2 | S11: 2 | T11: 2 | U11: =IFERROR(INDEX(AIRPORT_DB!$L:$L,MATCH($A11,AIRPORT_DB!$A:$A,0))+1,2) -> 1 | V11: =ROUND(AVERAGE(LARGE(B11:K11,{1,2,3}))+AVERAGE(LARGE(L11:U11,{1,2,3}))-1,0)+IF(INDEX(AIRPORT_DB!$L:$L,MATCH($A11,AIRPORT_DB!$A:$A,0))>=1,1,0)+IF(AB11="C",1,0) -> 6 | W11: =IF(V11<=6,"LOW",IF(V11<=9,"MEDIUM",IF(V11<=12,"HIGH","EXTREME"))) -> LOW | X11: =IF(W11="EXTREME","OPS MANAGER APPROVAL REQUIRED",IF(AND(W11="HIGH",AB11="C"),"OPS MANAGER APPROVAL REQUIRED",IF(W11="HIGH","CAPTAIN REVIEW / DISPATCH COORDINATION","DISPATCH OK"))) -> DISPATCH OK | Y11: STRICT TERRAIN/OBSTACLE PROC COMPLIANCE; REVIEW MSA / MISSED APCH / CHECK TAF/METAR/NOTAM; CONTAMINATION / DE-ICE PLAN | Z11: OpenAI - V9 setup | AA11: 2026-03-08 | AB11: A | AC11: =ROUND(AVERAGE(LARGE(B11:K11,{1,2,3})),0) -> 4 | AD11: =ROUND(AVERAGE(LARGE(L11:U11,{1,2,3})),0) -> 3 | AE11: 3 | AF11: 2
A12: EDDH | B12: 4 | C12: 4 | D12: 4 | E12: 4 | F12: 4 | G12: 3 | H12: 2 | I12: 3 | J12: 3 | K12: =IFERROR(INDEX(AIRPORT_DB!$L:$L,MATCH($A12,AIRPORT_DB!$A:$A,0))+1,2) -> 1 | L12: 4 | M12: 3 | N12: 3 | O12: 3 | P12: 3 | Q12: 2 | R12: 2 | S12: 2 | T12: 2 | U12: =IFERROR(INDEX(AIRPORT_DB!$L:$L,MATCH($A12,AIRPORT_DB!$A:$A,0))+1,2) -> 1 | V12: =ROUND(AVERAGE(LARGE(B12:K12,{1,2,3}))+AVERAGE(LARGE(L12:U12,{1,2,3}))-1,0)+IF(INDEX(AIRPORT_DB!$L:$L,MATCH($A12,AIRPORT_DB!$A:$A,0))>=1,1,0)+IF(AB12="C",1,0) -> 6 | W12: =IF(V12<=6,"LOW",IF(V12<=9,"MEDIUM",IF(V12<=12,"HIGH","EXTREME"))) -> LOW | X12: =IF(W12="EXTREME","OPS MANAGER APPROVAL REQUIRED",IF(AND(W12="HIGH",AB12="C"),"OPS MANAGER APPROVAL REQUIRED",IF(W12="HIGH","CAPTAIN REVIEW / DISPATCH COORDINATION","DISPATCH OK"))) -> DISPATCH OK | Y12: BRIEF APP/TRAFFIC FLOW; STABILIZED APPROACH / GO-AROUND READY | Z12: OpenAI - V9 setup | AA12: 2026-03-08 | AB12: B | AC12: =ROUND(AVERAGE(LARGE(B12:K12,{1,2,3})),0) -> 4 | AD12: =ROUND(AVERAGE(LARGE(L12:U12,{1,2,3})),0) -> 3 | AE12: 3 | AF12: 2
A13: EDDK | B13: 4 | C13: 4 | D13: 4 | E13: 4 | F13: 4 | G13: 3 | H13: 2 | I13: 3 | J13: 4 | K13: =IFERROR(INDEX(AIRPORT_DB!$L:$L,MATCH($A13,AIRPORT_DB!$A:$A,0))+1,2) -> 1 | L13: 4 | M13: 3 | N13: 3 | O13: 3 | P13: 3 | Q13: 2 | R13: 2 | S13: 2 | T13: 3 | U13: =IFERROR(INDEX(AIRPORT_DB!$L:$L,MATCH($A13,AIRPORT_DB!$A:$A,0))+1,2) -> 1 | V13: =ROUND(AVERAGE(LARGE(B13:K13,{1,2,3}))+AVERAGE(LARGE(L13:U13,{1,2,3}))-1,0)+IF(INDEX(AIRPORT_DB!$L:$L,MATCH($A13,AIRPORT_DB!$A:$A,0))>=1,1,0)+IF(AB13="C",1,0) -> 6 | W13: =IF(V13<=6,"LOW",IF(V13<=9,"MEDIUM",IF(V13<=12,"HIGH","EXTREME"))) -> LOW | X13: =IF(W13="EXTREME","OPS MANAGER APPROVAL REQUIRED",IF(AND(W13="HIGH",AB13="C"),"OPS MANAGER APPROVAL REQUIRED",IF(W13="HIGH","CAPTAIN REVIEW / DISPATCH COORDINATION","DISPATCH OK"))) -> DISPATCH OK | Y13: BRIEF APP/TRAFFIC FLOW; STABILIZED APPROACH / GO-AROUND READY | Z13: OpenAI - V9 setup | AA13: 2026-03-08 | AB13: B | AC13: =ROUND(AVERAGE(LARGE(B13:K13,{1,2,3})),0) -> 4 | AD13: =ROUND(AVERAGE(LARGE(L13:U13,{1,2,3})),0) -> 3 | AE13: 3 | AF13: 2
... A561: ENBR | B561: 2 | C561: 5 | D561: 4 | E561: 3 | F561: 3 | G561: 3 | H561: 2 | I561: 2 | J561: 4 | K561: =IFERROR(INDEX(AIRPORT_DB!$L:$L,MATCH($A561,AIRPORT_DB!$A:$A,0))+1,2) -> 1 | L561: 2 | M561: 4 | N561: 4 | O561: 2 | P561: 2 | Q561: 2 | R561: 2 | S561: 2 | T561: 3 | U561: =IFERROR(INDEX(AIRPORT_DB!$L:$L,MATCH($A561,AIRPORT_DB!$A:$A,0))+1,2) -> 1 | V561: =ROUND(AVERAGE(LARGE(B561:K561,{1,2,3}))+AVERAGE(LARGE(L561:U561,{1,2,3}))-1,0)+IF(INDEX(AIRPORT_DB!$L:$L,MATCH($A561,AIRPORT_DB!$A:$A,0))>=1,1,0)+IF(AB561="C",1,0) -> 7 | W561: =IF(V561<=6,"LOW",IF(V561<=9,"MEDIUM",IF(V561<=12,"HIGH","EXTREME"))) -> MEDIUM | X561: =IF(W561="EXTREME","OPS MANAGER APPROVAL REQUIRED",IF(AND(W561="HIGH",AB561="C"),"OPS MANAGER APPROVAL REQUIRED",IF(W561="HIGH","CAPTAIN REVIEW / DISPATCH COORDINATION","DISPATCH OK"))) -> DISPATCH OK | Y561: STRICT TERRAIN/OBSTACLE PROC COMPLIANCE; REVIEW MSA / MISSED APCH | Z561: OpenAI - V9 setup | AA561: 2026-03-08 | AB561: B | AC561: =ROUND(AVERAGE(LARGE(B561:K561,{1,2,3})),0) -> 4 | AD561: =ROUND(AVERAGE(LARGE(L561:U561,{1,2,3})),0) -> 4 | AE561: 3 | AF561: 2
A562: LTFC | B562: 3 | C562: 4 | D562: 4 | E562: 4 | F562: 3 | G562: 3 | H562: 2 | I562: 3 | J562: 4 | K562: =IFERROR(INDEX(AIRPORT_DB!$L:$L,MATCH($A241,AIRPORT_DB!$A:$A,0))+1,2) -> 1 | L562: 2 | M562: 3 | N562: 3 | O562: 3 | P562: 2 | Q562: 2 | R562: 2 | S562: 2 | T562: 3 | U562: =IFERROR(INDEX(AIRPORT_DB!$L:$L,MATCH($A241,AIRPORT_DB!$A:$A,0))+1,2) -> 1 | V562: =ROUND(AVERAGE(LARGE(B241:K241,{1,2,3}))+AVERAGE(LARGE(L241:U241,{1,2,3}))-1,0)+IF(INDEX(AIRPORT_DB!$L:$L,MATCH($A241,AIRPORT_DB!$A:$A,0))>=1,1,0)+IF(AB241="C",1,0) -> 6 | W562: =IF(V241<=6,"LOW",IF(V241<=9,"MEDIUM",IF(V241<=12,"HIGH","EXTREME"))) -> LOW | X562: =IF(W241="EXTREME","OPS MANAGER APPROVAL REQUIRED",IF(AND(W241="HIGH",AB241="C"),"OPS MANAGER APPROVAL REQUIRED",IF(W241="HIGH","CAPTAIN REVIEW / DISPATCH COORDINATION","DISPATCH OK"))) -> DISPATCH OK | Y562: STRICT TERRAIN/OBSTACLE PROC COMPLIANCE; REVIEW MSA / MISSED APCH / CHECK TAF/METAR/NOTAM; CONTAMINATION / DE-ICE PLAN | Z562: OpenAI - V9 setup | AA562: 2026-03-08 | AB562: A | AC562: =ROUND(AVERAGE(LARGE(B241:K241,{1,2,3})),0) -> 4 | AD562: =ROUND(AVERAGE(LARGE(L241:U241,{1,2,3})),0) -> 3 | AE562: 3 | AF562: 2
A563: ZUTF | B563: 3 | C563: 4 | D563: 4 | E563: 4 | F563: 3 | G563: 3 | H563: 2 | I563: 3 | J563: 3 | K563: =IFERROR(INDEX(AIRPORT_DB!$L:$L,MATCH($A550,AIRPORT_DB!$A:$A,0))+1,2) -> 1 | L563: 2 | M563: 3 | N563: 3 | O563: 3 | P563: 2 | Q563: 2 | R563: 2 | S563: 2 | T563: 2 | U563: =IFERROR(INDEX(AIRPORT_DB!$L:$L,MATCH($A550,AIRPORT_DB!$A:$A,0))+1,2) -> 1 | V563: =ROUND(AVERAGE(LARGE(B550:K550,{1,2,3}))+AVERAGE(LARGE(L550:U550,{1,2,3}))-1,0)+IF(INDEX(AIRPORT_DB!$L:$L,MATCH($A550,AIRPORT_DB!$A:$A,0))>=1,1,0)+IF(AB550="C",1,0) -> 6 | W563: =IF(V550<=6,"LOW",IF(V550<=9,"MEDIUM",IF(V550<=12,"HIGH","EXTREME"))) -> LOW | X563: =IF(W550="EXTREME","OPS MANAGER APPROVAL REQUIRED",IF(AND(W550="HIGH",AB550="C"),"OPS MANAGER APPROVAL REQUIRED",IF(W550="HIGH","CAPTAIN REVIEW / DISPATCH COORDINATION","DISPATCH OK"))) -> DISPATCH OK | Y563: STRICT TERRAIN/OBSTACLE PROC COMPLIANCE; REVIEW MSA / MISSED APCH / CHECK TAF/METAR/NOTAM; CONTAMINATION / DE-ICE PLAN | Z563: OpenAI - V9 setup | AA563: 2026-03-08 | AB563: B | AC563: =ROUND(AVERAGE(LARGE(B550:K550,{1,2,3})),0) -> 4 | AD563: =ROUND(AVERAGE(LARGE(L550:U550,{1,2,3})),0) -> 3 | AE563: 2 | AF563: 2
A564: LTAF | B564: 3 | C564: 4 | D564: 4 | E564: 4 | F564: 3 | G564: 3 | H564: 2 | I564: 3 | J564: 3 | K564: =IFERROR(INDEX(AIRPORT_DB!$L:$L,MATCH($A235,AIRPORT_DB!$A:$A,0))+1,2) -> 1 | L564: 2 | M564: 3 | N564: 3 | O564: 3 | P564: 2 | Q564: 2 | R564: 2 | S564: 2 | T564: 2 | U564: =IFERROR(INDEX(AIRPORT_DB!$L:$L,MATCH($A235,AIRPORT_DB!$A:$A,0))+1,2) -> 1 | V564: =ROUND(AVERAGE(LARGE(B235:K235,{1,2,3}))+AVERAGE(LARGE(L235:U235,{1,2,3}))-1,0)+IF(INDEX(AIRPORT_DB!$L:$L,MATCH($A235,AIRPORT_DB!$A:$A,0))>=1,1,0)+IF(AB235="C",1,0) -> 6 | W564: =IF(V235<=6,"LOW",IF(V235<=9,"MEDIUM",IF(V235<=12,"HIGH","EXTREME"))) -> LOW | X564: =IF(W235="EXTREME","OPS MANAGER APPROVAL REQUIRED",IF(AND(W235="HIGH",AB235="C"),"OPS MANAGER APPROVAL REQUIRED",IF(W235="HIGH","CAPTAIN REVIEW / DISPATCH COORDINATION","DISPATCH OK"))) -> DISPATCH OK | Y564: STRICT TERRAIN/OBSTACLE PROC COMPLIANCE; REVIEW MSA / MISSED APCH / CHECK TAF/METAR/NOTAM; CONTAMINATION / DE-ICE PLAN | Z564: OpenAI - V9 setup | AA564: 2026-03-08 | AB564: A | AC564: =ROUND(AVERAGE(LARGE(B235:K235,{1,2,3})),0) -> 4 | AD564: =ROUND(AVERAGE(LARGE(L235:U235,{1,2,3})),0) -> 3 | AE564: 2 | AF564: 2
A565: UASS | B565: 3 | C565: 4 | D565: 2 | E565: 4 | F565: 3 | G565: 3 | H565: 2 | I565: 3 | J565: 3 | K565: =IFERROR(INDEX(AIRPORT_DB!$L:$L,MATCH($A354,AIRPORT_DB!$A:$A,0))+1,2) -> 1 | L565: 2 | M565: 3 | N565: 2 | O565: 3 | P565: 2 | Q565: 2 | R565: 2 | S565: 2 | T565: 2 | U565: =IFERROR(INDEX(AIRPORT_DB!$L:$L,MATCH($A354,AIRPORT_DB!$A:$A,0))+1,2) -> 1 | V565: =ROUND(AVERAGE(LARGE(B354:K354,{1,2,3}))+AVERAGE(LARGE(L354:U354,{1,2,3}))-1,0)+IF(INDEX(AIRPORT_DB!$L:$L,MATCH($A354,AIRPORT_DB!$A:$A,0))>=1,1,0)+IF(AB354="C",1,0) -> 5 | W565: =IF(V354<=6,"LOW",IF(V354<=9,"MEDIUM",IF(V354<=12,"HIGH","EXTREME"))) -> LOW | X565: =IF(W354="EXTREME","OPS MANAGER APPROVAL REQUIRED",IF(AND(W354="HIGH",AB354="C"),"OPS MANAGER APPROVAL REQUIRED",IF(W354="HIGH","CAPTAIN REVIEW / DISPATCH COORDINATION","DISPATCH OK"))) -> DISPATCH OK | Y565: STRICT TERRAIN/OBSTACLE PROC COMPLIANCE; REVIEW MSA / MISSED APCH / STERILE COMMS; FULL READBACK / QUERY IF DOUBT | Z565: OpenAI - V9 setup | AA565: 2026-03-08 | AB565: A | AC565: =ROUND(AVERAGE(LARGE(B354:K354,{1,2,3})),0) -> 4 | AD565: =ROUND(AVERAGE(LARGE(L354:U354,{1,2,3})),0) -> 3 | AE565: 2 | AF565: 2
A566: UAKD | B566: 3 | C566: 4 | D566: 2 | E566: 4 | F566: 3 | G566: 3 | H566: 2 | I566: 3 | J566: 3 | K566: =IFERROR(INDEX(AIRPORT_DB!$L:$L,MATCH($A355,AIRPORT_DB!$A:$A,0))+1,2) -> 1 | L566: 2 | M566: 3 | N566: 2 | O566: 3 | P566: 2 | Q566: 2 | R566: 2 | S566: 2 | T566: 2 | U566: =IFERROR(INDEX(AIRPORT_DB!$L:$L,MATCH($A355,AIRPORT_DB!$A:$A,0))+1,2) -> 1 | V566: =ROUND(AVERAGE(LARGE(B355:K355,{1,2,3}))+AVERAGE(LARGE(L355:U355,{1,2,3}))-1,0)+IF(INDEX(AIRPORT_DB!$L:$L,MATCH($A355,AIRPORT_DB!$A:$A,0))>=1,1,0)+IF(AB355="C",1,0) -> 5 | W566: =IF(V355<=6,"LOW",IF(V355<=9,"MEDIUM",IF(V355<=12,"HIGH","EXTREME"))) -> LOW | X566: =IF(W355="EXTREME","OPS MANAGER APPROVAL REQUIRED",IF(AND(W355="HIGH",AB355="C"),"OPS MANAGER APPROVAL REQUIRED",IF(W355="HIGH","CAPTAIN REVIEW / DISPATCH COORDINATION","DISPATCH OK"))) -> DISPATCH OK | Y566: STRICT TERRAIN/OBSTACLE PROC COMPLIANCE; REVIEW MSA / MISSED APCH / STERILE COMMS; FULL READBACK / QUERY IF DOUBT | Z566: OpenAI - V9 setup | AA566: 2026-03-08 | AB566: A | AC566: =ROUND(AVERAGE(LARGE(B355:K355,{1,2,3})),0) -> 4 | AD566: =ROUND(AVERAGE(LARGE(L355:U355,{1,2,3})),0) -> 3 | AE566: 2 | AF566: 2

Sheet MATRIX_V5
A1: ICAO INPUT | D1: PPS ADD-ON LINE (auto)
A2: =UPPER(TRIM(PPS!B1)) -> LTCG | D2: =IF(D19="","", "CONSIDERED " & D19 & " RISK LEVEL (SxL MAX=" & D18 & ")" & IF(D20<>"", CHAR(10)&D20,"") & IF(D22<>"", CHAR(10)&"MITIGATION: " & D22,"")) -> CONSIDERED LOW RISK LEVEL (SxL MAX=0)
A3: NOT: S/L değerlerini B ve C sütunlarına gir. İstersen bu değerleri MATRIX_STORE içinde ilgili ICAO satırına kopyalayarak kalıcı hale getirebilirsin.
A4: RISK MATRIX (S x L)
A6: Risk Topic | B6: Severity (1-5) | C6: Likelihood (1-5) | D6: Score | F6: LEGEND
A7: 1. Approach & Traffic Density | D7: =IF(OR(B7="",C7=""),"",B7*C7) | F7: LOW (1-8)
A8: 2. Obstacles / Terrain (Mania) | D8: =IF(OR(B8="",C8=""),"",B8*C8) | F8: MEDIUM (9-15)
A9: 3. Seasonal / Meteorology | D9: =IF(OR(B9="",C9=""),"",B9*C9) | F9: HIGH (16-25)
A10: 4. ATC Phraseology / Language | D10: =IF(OR(B10="",C10=""),"",B10*C10)
A11: 5. Complex Taxi Routings | D11: =IF(OR(B11="",C11=""),"",B11*C11)
A12: 6. RWY Ops / Late Clearance / Dep-Arr Separation | D12: =IF(OR(B12="",C12=""),"",B12*C12)
A13: 7. Security / Terror Threat | D13: =IF(OR(B13="",C13=""),"",B13*C13)
A14: 8. Handling / Fuel / Pax Support | D14: =IF(OR(B14="",C14=""),"",B14*C14)
A15: 9. Radio Nav / GNSS Reliability | D15: =IF(OR(B15="",C15=""),"",B15*C15)
A16: 10. Other Local Constraints (Slot/Curfew/Noise/etc.) | D16: =IF(OR(B16="",C16=""),"",B16*C16)
A18: OVERALL SCORE (MAX of row scores) | D18: =MAX(D7:D16) -> 0
A19: RISK LEVEL | D19: =IF(D18="","",IF(D18<=8,"LOW",IF(D18<=15,"MEDIUM","HIGH"))) -> LOW
A20: OPS APPROVAL FLAG | D20: =IF(D19="HIGH","OPS APPROVAL REQUIRED","")
A22: MITIGATION (free text)

Sheet RISK_HISTORY
A1: Timestamp | B1: ICAO | C1: Operation Type | D1: Severity | E1: Likelihood | F1: Risk Score | G1: Risk Level | H1: OPS Approval | I1: Mitigation Code | J1: Mitigation Text | K1: Pilot/Dispatcher | L1: Notes

Sheet RISK_FLAGS
A1: ICAO | B1: Terrain | C1: Slot | D1: Curfew | E1: Parallel RWY | F1: Taxi Complexity | G1: Weather Risk | H1: Security Risk | I1: Overall (MAX)
A2: DAAG | B2: 1 | C2: 1 | D2: 1 | E2: 1 | F2: 1 | H2: 1 | I2: =MAX(B2:H2) -> 1
A3: EBBR | B3: 3 | C3: 2 | D3: 2 | E3: 4 | F3: 2 | G3: 4 | H3: 2 | I3: =MAX(B3:H3) -> 4
A4: EBCI | B4: 3 | C4: 2 | D4: 1 | E4: 1 | F4: 2 | G4: 4 | H4: 2 | I4: =MAX(B4:H4) -> 4
A5: EBLG | B5: 3 | C5: 2 | D5: 2 | E5: 1 | F5: 2 | G5: 4 | H5: 2 | I5: =MAX(B5:H5) -> 4
A6: EBOS | B6: 3 | C6: 2 | D6: 1 | E6: 1 | F6: 2 | G6: 4 | H6: 2 | I6: =MAX(B6:H6) -> 4
A7: EDDB | B7: 3 | C7: 3 | D7: 1 | E7: 3 | F7: 3 | G7: 4 | H7: 2 | I7: =MAX(B7:H7) -> 4
A8: EDDC | B8: 3 | C8: 2 | D8: 1 | E8: 1 | F8: 2 | G8: 4 | H8: 2 | I8: =MAX(B8:H8) -> 4
A9: EDDE | B9: 3 | C9: 2 | D9: 1 | E9: 1 | F9: 2 | G9: 4 | H9: 2 | I9: =MAX(B9:H9) -> 4
A10: EDDF | B10: 3 | C10: 3 | D10: 1 | E10: 4 | F10: 3 | G10: 4 | H10: 2 | I10: =MAX(B10:H10) -> 4
A11: EDDG | B11: 3 | C11: 2 | D11: 2 | E11: 1 | F11: 2 | G11: 4 | H11: 2 | I11: =MAX(B11:H11) -> 4
A12: EDDH | B12: 3 | C12: 3 | D12: 1 | E12: 1 | F12: 3 | G12: 4 | H12: 2 | I12: =MAX(B12:H12) -> 4
A13: EDDK | B13: 3 | C13: 3 | D13: 1 | E13: 1 | F13: 3 | G13: 4 | H13: 2 | I13: =MAX(B13:H13) -> 4
A14: EDDL | B14: 3 | C14: 3 | D14: 3 | E14: 1 | F14: 3 | G14: 4 | H14: 2 | I14: =MAX(B14:H14) -> 4
... A561: ENBR | B561: 4 | C561: 1 | D561: 1 | E561: 1 | F561: 2 | G561: 4 | H561: 1 | I561: =MAX(B561:H561) -> 4

Sheet MATRIX_V7
A1: ICAO | B1: Operation Type | C1: Severity | D1: Likelihood | E1: Risk Score | F1: Risk Level | G1: OPS Approval | H1: Mitigation Code | I1: Mitigation Text | J1: Pilot/Dispatcher | K1: Timestamp
A2: =UPPER(TRIM(PPS!B1)) -> LTCG | K2: =TEXT(NOW(),"yyyy-mm-dd hh:mm") -> 2026-mm-11 hh:mm
A4: LOG KAYDI: | B4: MATRIX_V7 satır-2'yi kopyala → RISK_HISTORY'de ilk boş satıra 'Değerler' olarak yapıştır.

Sheet MATRIX_V8
A1: ICAO | B1: Operation Type | C1: Base Severity | D1: Base Likelihood | E1: Total Risk Score | F1: Risk Level | G1: OPS Approval | H1: Airport Category | I1: Mitigation Text | J1: Pilot/Dispatcher | K1: Timestamp | L1: Night Ops (+1) | M1: Strong XW/Gust (+2) | N1: RWY Wet/Contam (+2) | O1: Low Vis/TS (+2) | P1: Crew Low FAM (+2) | Q1: Base Max Score | R1: Pilot Add-On | S1: DB Updated On | T1: Base Risk Level
A2: =UPPER(TRIM(PPS!B1)) -> LTCG | B2: Mixed | C2: =IF(A2="","",IFERROR(INDEX(MATRIX_STORE!$AC:$AC,MATCH(A2,MATRIX_STORE!$A:$A,0)),0)) -> 4 | D2: =IF(A2="","",IFERROR(INDEX(MATRIX_STORE!$AD:$AD,MATCH(A2,MATRIX_STORE!$A:$A,0)),0)) -> 3 | E2: =IF(A2="","",Q2+R2) -> 6 | F2: =IF(E2="","",IF(E2<=6,"LOW",IF(E2<=9,"MEDIUM",IF(E2<=12,"HIGH","EXTREME")))) -> LOW | G2: =IF(F2="","",IF(F2="EXTREME","OPS MANAGER APPROVAL REQUIRED",IF(AND(F2="HIGH",H2="C"),"OPS MANAGER APPROVAL REQUIRED",IF(F2="HIGH","CAPTAIN REVIEW / DISPATCH COORDINATION","DISPATCH OK")))) -> DISPATCH OK | H2: =IF(A2="","",IFERROR(INDEX(MATRIX_STORE!$AB:$AB,MATCH(A2,MATRIX_STORE!$A:$A,0)),"")) -> B | I2: =IF(A2="","",IFERROR(INDEX(MATRIX_STORE!$Y:$Y,MATCH(A2,MATRIX_STORE!$A:$A,0)),"")&IF(R2>0," + REVIEW PILOT INPUT ITEMS","")) -> STRICT TERRAIN/OBSTACLE PROC COMPLIANCE; REVIEW MSA / MISSED APCH / CHECK TAF/METAR/NOTAM; CONTAMINATION / DE-ICE PLAN | K2: =TEXT(NOW(),"yyyy-mm-dd hh:mm") -> 2026-mm-11 hh:mm | L2: 0 | M2: 0 | N2: 0 | O2: 0 | P2: 0 | Q2: =IF(A2="","",IFERROR(INDEX(MATRIX_STORE!$V:$V,MATCH(A2,MATRIX_STORE!$A:$A,0)),0)) -> 6 | R2: =SUM(L2:O2)+P2 -> 0 | S2: =IF(A2="","",IFERROR(INDEX(MATRIX_STORE!$AA:$AA,MATCH(A2,MATRIX_STORE!$A:$A,0)),"")) -> 2026-03-08 | T2: =IF(A2="","",IFERROR(INDEX(MATRIX_STORE!$W:$W,MATCH(A2,MATRIX_STORE!$A:$A,0)),"")) -> LOW
A4: NOT: | B4: Turuncu başlıklı alanlar pilot/dispatcher girdisidir. L:P hücrelerine 0 / 1 / 2 girerek operasyonel add-on risk ekleyin. Base risk MATRIX_STORE’dan otomatik gelir. AIRPORT_DB içindeki AD ELEV / MAX TMA MSA skoru 0/1/2 olarak çalışır: eşik altı 0, tek yüksek eşik 1, çok yüksek eşik 2.
A6: AUTO LOG: | B6: Makro (XLSM) kurulduysa 'SAVE RISK LOG' butonu ile kayıt otomatik RISK_HISTORY’ye eklenir.
A7: SAVE RISK LOG

Sheet VBA_INSTALL
A1: RAQ FORM — PDF BUTONU KURULUM KILAVUZU
A3: Bu sayfadaki VBA kodunu bir kez kurarak RAQ_FORM sayfasına PDF butonu ekleyebilirsiniz.
A5: ▶ ADIM 1 — Dosyayı .xlsm olarak kaydedin
A6: Dosya › Farklı Kaydet › Excel Makro Etkin Çalışma Kitabı (*.xlsm)
A7: ▶ ADIM 2 — VBA Editörünü açın
A8: Alt + F11 tuş kombinasyonuna basın
A9: ▶ ADIM 3 — Yeni modül oluşturun
A10: Insert › Module menüsünü seçin
A11: ▶ ADIM 4 — Aşağıdaki kodu yapıştırın
A12: Ctrl+A ile tümünü seçip silin, sonra aşağıdaki kodu yapıştırın
A14: ━━━━━━━━━━━━━━━━━━━━━━━━━━━━━━━━━━━━━━━━━━━━━━━━━━━━━━━━━━━━━━━━━━━━━━━━━━━━━━━━━━━━━━━━━━━━━━━━━━━━━━━━━━━━━━
A15: '══════════════════════════════════════════════════════════════════════
... A89: ADIM 5 — RAQ_FORM sayfasında Insert › Shapes ile bir dikdörtgen çizin → Sağ tık → Assign Macro → RAQ_PDF_Olustur seçin → Butona tıklayınca PDF sorulsun

Sheet RAQ_FORM
A2: REC HAVACILIK ✈ YOL VE MEYDAN YETERLİLİK EĞİTİM FORMU
A3: ICAO → | E3: =IFERROR("✔ "&VLOOKUP(C3,AIRPORT_DB!$A:$B,2,FALSE)&" CAT: "&VLOOKUP(C3,AIRPORT_DB!$A:$I,9,FALSE),"⚠ ICAO bulunamadı") -> ⚠ ICAO bulunamadı
A5: FLIGHT DETAILS
A6: Date | B6: A/C Type | C6: PIC | F6: SIC
B7: TC-REC
A9: AERODROME
A10: Airport Name | D10: ICAO | E10: Category | G10: Last Updated
A11: =IFERROR(VLOOKUP(C3,AIRPORT_DB!$A:$B,2,FALSE),"-") -> - | D11: =IF(C3="","",C3) | E11: =IFERROR(VLOOKUP(C3,AIRPORT_DB!$A:$I,9,FALSE),"-") -> - | G11: =IFERROR(TEXT(VLOOKUP(C3,AIRPORT_DB!$A:$H,7,FALSE),"YYYY-MM-DD"),"-") -> -
A13: FAMILIARIZATION CONDUCTED BY
A14: Self Briefing | E14: Local Authority
A15: ☐ Self Briefing | E15: ☐ Local Authority
A17: FOLLOWING ITEMS WERE BRIEFED AND FAMILIARIZED FOR THE ROUTE FLOWN
A18: ☐ Terrain and Safe Altitudes
A19: ☐ Communication and ATC Facilities
A20: ☐ Search & Rescue Procedures
A21: ☐ Airport Layout
A22: ☐ Approach Aids
A23: ☐ Instrument Approach and Hold Procedures
A24: ☐ Operating Minima
A26: SPECIAL ITEMS BRIEFED DUE TO AERODROME CATEGORY
A27: ☐ (1) Non-standard approach aids or approach patterns
A28: ☐ (2) Unusual local weather conditions
A29: ☐ (3) Unusual characteristics or performance limitations
... A34: SECTION 1 – Traffic / ATC / Taxi / Runway Ops
A35: =IFERROR(VLOOKUP(C3,AIRPORT_DB!$A:$C,3,FALSE),"N/A – ICAO not found") -> N/A – ICAO not found
A37: SECTION 2 – Meteorology / Wind
A38: =IFERROR(VLOOKUP(C3,AIRPORT_DB!$A:$D,4,FALSE),"N/A – ICAO not found") -> N/A – ICAO not found
A40: SECTION 3 – Security / Handling / Navigation
A41: =IFERROR(VLOOKUP(C3,AIRPORT_DB!$A:$E,5,FALSE),"N/A – ICAO not found") -> N/A – ICAO not found
A44: AERODROME RISK SUMMARY (AUTO – DATABASE)
A45: =IFERROR("RISK LEVEL: "&VLOOKUP(C3,MATRIX_STORE!$A:$W,23,FALSE)&" | CAT: "&VLOOKUP(C3,AIRPORT_DB!$A:$I,9,FALSE)&" | "&VLOOKUP(C3,MATRIX_STORE!$A:$X,24,FALSE)&CHAR(10)&"MITIGATION: "&VLOOKUP(C3,MATRIX_STORE!$A:$Y,25,FALSE),"ICAO veritabanında bulunamadı") -> ICAO veritabanında bulunamadı
A47: I hereby certify that route and aerodrome familiarization was completed for the flight in accordance with AMC1 ORO.FC.105 b(2);c and OM PART C.
A48: Completed by: | G48: =TEXT(TODAY(),"YYYY-MM-DD") -> 2026-MM-00
A50: ⬇ PDF OLUŞTURMAK İÇİN: Makrolar etkinse 📄 PDF OLUŞTUR butonuna tıklayın – veya Dosya › Dışa Aktar › PDF/XPS seçeneğini kullanın
